Workbook

Sheet 📊 Dashboard
A1: 📊 APEX ROUTE LOGISTICS — MONTHLY DASHBOARD
A2: All figures auto-calculated from Income & Expenses tabs
A4: 💰 TOTAL INCOME | C4: 💸 TOTAL EXPENSES | E4: 📈 NET PROFIT | G4: 💳 CNG BILL DUE
A5: =SUM(Income!F4,Income!G4) -> 0 | C5: =SUM(Expenses!F4,Expenses!G4,Expenses!H4) -> 0 | E5: =B5-B6 -> 0 | G5: =SUMIF(Expenses!D5:D10000,"CNG/Petrol",Expenses!H5:H10000) -> 0
A7: 💰 Income by Category | E7: 💸 Expense by Category
A8: Vendor/DCO | B8: =SUMIF(Income!D5:D10000,"Vendor/DCO",Income!F5:F10000)+SUMIF(Income!D5:D10000,"Vendor/DCO",Income!G5:G10000) -> 0 | C8: =IFERROR(B8/SUM(Income!F5:F10000,Income!G5:G10000),0) -> 0 | E8: CNG/Petrol | F8: =SUMIF(Expenses!D5:D10000,"CNG/Petrol",Expenses!F5:F10000)+SUMIF(Expenses!D5:D10000,"CNG/Petrol",Expenses!G5:G10000)+SUMIF(Expenses!D5:D10000,"CNG/Petrol",Expenses!H5:H10000) -> 0 | G8: =IFERROR(F8/SUM(Expenses!F5:F10000,Expenses!G5:G10000,Expenses!H5:H10000),0) -> 0 | H8: 💳 CC
A9: Porter | B9: =SUMIF(Income!D5:D10000,"Porter",Income!F5:F10000)+SUMIF(Income!D5:D10000,"Porter",Income!G5:G10000) -> 0 | C9: =IFERROR(B9/SUM(Income!F5:F10000,Income!G5:G10000),0) -> 0 | E9: Maintenance | F9: =SUMIF(Expenses!D5:D10000,"Maintenance",Expenses!F5:F10000)+SUMIF(Expenses!D5:D10000,"Maintenance",Expenses!G5:G10000)+SUMIF(Expenses!D5:D10000,"Maintenance",Expenses!H5:H10000) -> 0 | G9: =IFERROR(F9/SUM(Expenses!F5:F10000,Expenses!G5:G10000,Expenses!H5:H10000),0) -> 0
A10: Factory | B10: =SUMIF(Income!D5:D10000,"Factory",Income!F5:F10000)+SUMIF(Income!D5:D10000,"Factory",Income!G5:G10000) -> 0 | C10: =IFERROR(B10/SUM(Income!F5:F10000,Income!G5:G10000),0) -> 0 | E10: Driver Expense | F10: =SUMIF(Expenses!D5:D10000,"Driver Expense",Expenses!F5:F10000)+SUMIF(Expenses!D5:D10000,"Driver Expense",Expenses!G5:G10000)+SUMIF(Expenses!D5:D10000,"Driver Expense",Expenses!H5:H10000) -> 0 | G10: =IFERROR(F10/SUM(Expenses!F5:F10000,Expenses!G5:G10000,Expenses!H5:H10000),0) -> 0
E11: Other | F11: =SUMIF(Expenses!D5:D10000,"Other",Expenses!F5:F10000)+SUMIF(Expenses!D5:D10000,"Other",Expenses!G5:G10000)+SUMIF(Expenses!D5:D10000,"Other",Expenses!H5:H10000) -> 0 | G11: =IFERROR(F11/SUM(Expenses!F5:F10000,Expenses!G5:G10000,Expenses!H5:H10000),0) -> 0
A13: 📅 Monthly Summary
A14: Month | B14: Total Income | C14: Total Expenses | D14: Net Profit | E14: Bank Balance | F14: Cash Balance | G14: CNG Bill | H14: Status
A15: Jan 2026 | B15: 0 | C15: 0 | D15: =C15-B15 -> 0 | E15: 0 | F15: 0 | G15: 0 | H15: =IF(D15>0,"✅ Profit",IF(D15<0,"❌ Loss","➖ Break Even")) -> ➖ Break Even
A16: Feb 2026 | B16: 0 | C16: 0 | D16: =C16-B16 -> 0 | E16: 0 | F16: 0 | G16: 0 | H16: =IF(D16>0,"✅ Profit",IF(D16<0,"❌ Loss","➖ Break Even")) -> ➖ Break Even
A17: Mar 2026 | B17: =SUM(Income!F4,Income!G4) -> 0 | C17: =SUM(Expenses!F4,Expenses!G4,Expenses!H4) -> 0 | D17: =C17-B17 -> 0 | E17: ='💳 Cash & Bank'!B10 -> 0 | F17: ='💳 Cash & Bank'!D10 -> 0 | G17: ='💳 Cash & Bank'!F10 -> 0 | H17: =IF(D17>0,"✅ Profit",IF(D17<0,"❌ Loss","➖ Break Even")) -> ➖ Break Even
A18: Apr 2026 | B18: 0 | C18: 0 | D18: =C18-B18 -> 0 | E18: 0 | F18: 0 | G18: 0 | H18: =IF(D18>0,"✅ Profit",IF(D18<0,"❌ Loss","➖ Break Even")) -> ➖ Break Even
A19: May 2026 | B19: 0 | C19: 0 | D19: =C19-B19 -> 0 | E19: 0 | F19: 0 | G19: 0 | H19: =IF(D19>0,"✅ Profit",IF(D19<0,"❌ Loss","➖ Break Even")) -> ➖ Break Even
A20: Jun 2026 | B20: 0 | C20: 0 | D20: =C20-B20 -> 0 | E20: 0 | F20: 0 | G20: 0 | H20: =IF(D20>0,"✅ Profit",IF(D20<0,"❌ Loss","➖ Break Even")) -> ➖ Break Even
A21: Jul 2026 | B21: 0 | C21: 0 | D21: =C21-B21 -> 0 | E21: 0 | F21: 0 | G21: 0 | H21: =IF(D21>0,"✅ Profit",IF(D21<0,"❌ Loss","➖ Break Even")) -> ➖ Break Even
A22: Aug 2026 | B22: 0 | C22: 0 | D22: =C22-B22 -> 0 | E22: 0 | F22: 0 | G22: 0 | H22: =IF(D22>0,"✅ Profit",IF(D22<0,"❌ Loss","➖ Break Even")) -> ➖ Break Even
A23: Sep 2026 | B23: 0 | C23: 0 | D23: =C23-B23 -> 0 | E23: 0 | F23: 0 | G23: 0 | H23: =IF(D23>0,"✅ Profit",IF(D23<0,"❌ Loss","➖ Break Even")) -> ➖ Break Even
A24: Oct 2026 | B24: 0 | C24: 0 | D24: =C24-B24 -> 0 | E24: 0 | F24: 0 | G24: 0 | H24: =IF(D24>0,"✅ Profit",IF(D24<0,"❌ Loss","➖ Break Even")) -> ➖ Break Even
A25: Nov 2026 | B25: 0 | C25: 0 | D25: =C25-B25 -> 0 | E25: 0 | F25: 0 | G25: 0 | H25: =IF(D25>0,"✅ Profit",IF(D25<0,"❌ Loss","➖ Break Even")) -> ➖ Break Even
A26: Dec 2026 | B26: 0 | C26: 0 | D26: =C26-B26 -> 0 | E26: 0 | F26: 0 | G26: 0 | H26: =IF(D26>0,"✅ Profit",IF(D26<0,"❌ Loss","➖ Break Even")) -> ➖ Break Even

Sheet Income
A1: 🚚 APEX ROUTE LOGISTICS — INCOME TRACKER
A2: Bot entries auto-append above the TOTAL row • Payment: UPI = Bank | Cash = Cash
A3: # | B3: Date | C3: Time | D3: Category | E3: Payment | F3: Bank (₹) | G3: Cash (₹) | H3: Remarks
A4: TOTAL INCOME | F4: =SUMIF(E5:E10000,"UPI",F5:F10000) -> 0 | G4: =SUMIF(E5:E10000,"Cash",G5:G10000) -> 0

Sheet Expenses
A1: 🚚 APEX ROUTE LOGISTICS — EXPENSE TRACKER
A2: Bot entries auto-append above the TOTAL row • CNG uses Credit Card • UPI = Bank | Cash = Cash
A3: # | B3: Date | C3: Time | D3: Category | E3: Payment | F3: Bank (₹) | G3: Cash (₹) | H3: Credit Card (₹) | I3: Remarks
A4: TOTAL EXPENSES | F4: =SUMIF(E5:E10000,"UPI",F5:F10000) -> 0 | G4: =SUMIF(E5:E10000,"Cash",G5:G10000) -> 0 | H4: =SUMIF(E5:E10000,"Credit Card",H5:H10000) -> 0

Sheet 💳 Cash & Bank
A1: 💳 APEX ROUTE LOGISTICS — CASH & BANK TRACKER
A2: Live balances auto-calculated from Income & Expenses sheets
A4: 💰 TOTAL INCOME | C4: 💸 TOTAL EXPENSES | E4: 📈 NET PROFIT
A5: =SUM(Income!F4,Income!G4) -> 0 | C5: =SUM(Expenses!F4,Expenses!G4,Expenses!H4) -> 0 | E5: =B5-B6 -> 0
A7: 🏦 BANK ACCOUNT | C7: 💵 CASH IN HAND | E7: 💳 CREDIT CARD BILL
A8: Income (UPI) | B8: =SUMIF(Income!E5:E10000,"UPI",Income!F5:F10000) -> 0 | C8: Income (Cash) | D8: =SUMIF(Income!E5:E10000,"Cash",Income!G5:G10000) -> 0 | E8: CNG/Petrol Total | F8: =SUMIF(Expenses!D5:D10000,"CNG/Petrol",Expenses!H5:H10000) -> 0
A9: Expenses (UPI) | B9: =SUMIF(Expenses!E5:E10000,"UPI",Expenses!F5:F10000) -> 0 | C9: Expenses (Cash) | D9: =SUMIF(Expenses!E5:E10000,"Cash",Expenses!G5:G10000) -> 0 | E9: Other Credit | F9: =SUMIF(Expenses!E5:E10000,"Credit Card",Expenses!H5:H10000)-F8 -> 0
A10: Net Bank Balance | B10: =B8-B9 -> 0 | C10: Net Cash Balance | D10: =D8-D9 -> 0 | E10: Total Due | F10: =F8+F9 -> 0
A12: 📋 CNG CREDIT CARD MONTHLY BILL TRACKER
A13: January | B13: February | C13: March | D13: April | E13: May | F13: June
A14: July | B14: August | C14: September | D14: October | E14: November | F14: December
A15: ⬜ Unpaid | B15: ⬜ Unpaid | C15: ⬜ Unpaid | D15: ⬜ Unpaid | E15: ⬜ Unpaid | F15: ⬜ Unpaid
A16: ⬜ Unpaid | B16: ⬜ Unpaid | C16: ⬜ Unpaid | D16: ⬜ Unpaid | E16: ⬜ Unpaid | F16: ⬜ Unpaid
